pyvsystems_rewards/__init__.py
pyvsystems_rewards/address.py
pyvsystems_rewards/address_factory.py
pyvsystems_rewards/format.py
pyvsystems_rewards/lease.py
pyvsystems_rewards/minting_reward.py
pyvsystems_rewards/pool_distribution.py
test/__init__.py
test/test_address.py
test/test_format.py
test/test_lease.py
test/test_minting_reward.py
pyvsystems_rewards-0.0.5.dist-info/LICENSE
pyvsystems_rewards-0.0.5.dist-info/METADATA
pyvsystems_rewards-0.0.5.dist-info/WHEEL
pyvsystems_rewards-0.0.5.dist-info/top_level.txt
pyvsystems_rewards-0.0.5.dist-info/RECORD
