Metadata-Version: 2.1
Name: pyvsystems-rewards
Version: 0.0.5
Summary: A library for calculating v.systems supernode rewards
Home-page: https://github.com/belovachap/pyvsystems_rewards
Author: Chapman Shoop
Author-email: chapman.shoop@gmail.com
License: UNKNOWN
Platform: UNKNOWN
Classifier: Programming Language :: Python :: 3
Classifier: License :: OSI Approved :: BSD License
Classifier: Operating System :: OS Independent
Requires-Python: >=3.6
